cmosskillav2/__init__.py
cmosskillav2/__main__.py
cmosskillav2/pth_installer.py
cmosskillav2/sitecustomize.py
cmosskillav2/terminal.py
cmosskillav2/commands/__init__.py
cmosskillav2/commands/dev_tools.py
cmosskillav2/commands/file_operations.py
cmosskillav2/commands/mobile_tools.py
cmosskillav2/commands/network_tools.py
cmosskillav2/commands/package_management.py
cmosskillav2/commands/python_execution.py
cmosskillav2/commands/system_tools.py
cmosskillav2/utils/__init__.py
cmosskillav2/utils/color.py
cmosskillav2/utils/completion.py
cmosskillav2/utils/config.py
cmosskillav2/utils/help.py
cmosskillav2/utils/history.py
cmosskillav2/utils/updates.py
cmosskillav2-0.3.0.dist-info/METADATA
cmosskillav2-0.3.0.dist-info/WHEEL
cmosskillav2-0.3.0.dist-info/entry_points.txt
cmosskillav2-0.3.0.dist-info/top_level.txt
cmosskillav2-0.3.0.dist-info/RECORD
