Metadata-Version: 2.2
Name: cmosskillav2
Version: 0.3.0
Summary: Cross-Platform Python Terminal Emulator with Enhanced Developer Utilities, Network Tools, and Mobile Support
Author-email: CMosSkillAV2 Developer <example@example.com>
Project-URL: Homepage, https://github.com/cmosskillav2/cmosskillav2
Project-URL: Bug Tracker, https://github.com/cmosskillav2/cmosskillav2/issues
Classifier: Development Status :: 3 - Alpha
Classifier: Environment :: Console
Classifier: Intended Audience :: Developers
Classifier: License :: OSI Approved :: MIT License
Classifier: Operating System :: OS Independent
Classifier: Programming Language :: Python :: 3
Classifier: Programming Language :: Python :: 3.9
Classifier: Programming Language :: Python :: 3.10
Classifier: Programming Language :: Python :: 3.11
Classifier: Topic :: Software Development :: Libraries :: Python Modules
Classifier: Topic :: Terminals
Classifier: Topic :: Utilities
Requires-Python: >=3.9
Requires-Dist: build>=1.2.2.post1
Requires-Dist: colorama>=0.4.6
Requires-Dist: setuptools>=76.0.0
Requires-Dist: twine>=6.1.0
